pygf2x.pyd
gint/__init__.py
gint/base.py
gint-0.2.0.dist-info/LICENSE
gint-0.2.0.dist-info/METADATA
gint-0.2.0.dist-info/WHEEL
gint-0.2.0.dist-info/top_level.txt
gint-0.2.0.dist-info/RECORD
