Metadata-Version: 2.1
Name: gint
Version: 0.2.0
Summary: A Python class for polynomial arithmetic over GF(2), based on Pythons built-in integers, efficiently implemented in C
Home-page: https://github.com/enok71/gint
Author: Oskar Enoksson
Author-email: enok@lysator.liu.se
License: UNKNOWN
Project-URL: Bug Tracker, https://github.com/enok71/gint/issues
Platform: UNKNOWN
Classifier: Programming Language :: Python :: 3
Classifier: License :: OSI Approved :: MIT License
Classifier: Operating System :: OS Independent
Requires-Python: >=3.6
License-File: LICENSE
Provides-Extra: tests
Requires-Dist: pytest ; extra == 'tests'
